rapidkode/__init__.py
rapidkode-1.0.6.dist-info/LICENSE
rapidkode-1.0.6.dist-info/METADATA
rapidkode-1.0.6.dist-info/WHEEL
rapidkode-1.0.6.dist-info/top_level.txt
rapidkode-1.0.6.dist-info/RECORD
