Metadata-Version: 2.1
Name: rapidkode
Version: 1.0.6
Summary: a powerful coding utility library
Home-page: https://github.com/sasivatsal7122/Rapidkode-package-pypi
Author: Sasi Vatsal
Author-email: sasivatsal7122@gmail.com
License: MIT
Keywords: rapidkode
Platform: UNKNOWN
Classifier: Development Status :: 5 - Production/Stable
Classifier: Intended Audience :: Education
Classifier: Operating System :: Microsoft :: Windows :: Windows 10
Classifier: License :: OSI Approved :: MIT License
Classifier: Programming Language :: Python :: 3
License-File: LICENSE
